miflora/__init__.py
miflora/_static_version.py
miflora/_version.py
miflora/miflora_poller.py
miflora/miflora_scanner.py
miflora-0.7.2.dist-info/LICENSE
miflora-0.7.2.dist-info/METADATA
miflora-0.7.2.dist-info/WHEEL
miflora-0.7.2.dist-info/top_level.txt
miflora-0.7.2.dist-info/RECORD
