Metadata-Version: 2.1
Name: miflora
Version: 0.7.2
Summary: Library to read data from Mi Flora sensor
Home-page: https://github.com/basnijholt/miflora
Author: Daniel Matuschek
Author-email: daniel@matuschek.net
Maintainer: Bas Nijholt
Maintainer-email: bas@nijho.lt
License: MIT
Keywords: plant sensor bluetooth low-energy ble
Platform: UNKNOWN
Classifier: Development Status :: 5 - Production/Stable
Classifier: Intended Audience :: Developers
Classifier: Topic :: System :: Hardware :: Hardware Drivers
Classifier: License :: OSI Approved :: MIT License
Classifier: Programming Language :: Python :: 3
Classifier: Programming Language :: Python :: 3.6
Classifier: Programming Language :: Python :: 3.7
Classifier: Programming Language :: Python :: 3.8
Requires-Python: >=3.6
License-File: LICENSE
Requires-Dist: btlewrap (<0.2,>=0.0.10)
Provides-Extra: testing
Requires-Dist: pytest ; extra == 'testing'
